License.txt
README.md
setup.py
Program/102017169.py
Program/__init__.py
Topsis_Reena_102017169.egg-info/PKG-INFO
Topsis_Reena_102017169.egg-info/SOURCES.txt
Topsis_Reena_102017169.egg-info/dependency_links.txt
Topsis_Reena_102017169.egg-info/entry_points.txt
Topsis_Reena_102017169.egg-info/requires.txt
Topsis_Reena_102017169.egg-info/top_level.txt