Metadata-Version: 2.1
Name: Topsis-Reena-102017169
Version: 1.0.4
Summary: A package -> Calculates Topsis Score and Rank them accordingly
Author: Reena Arora
Author-email: rarora_be20@thapar.edu
License: MIT
Keywords: python package ReenaArora
Classifier: Programming Language :: Python
Classifier: License :: OSI Approved :: MIT License
Classifier: Operating System :: OS Independent
License-File: License.txt
